{
  "updated": "2026-04-14 10:02",
  "total": 120,
  "offers": [
    {
      "id": 4329915,
      "titre": "Assistant (H/F) du directeur en charge de la vie scolaire",
      "etab": "",
      "ville": "Casablanca",
      "pays": "",
      "contrat": "Contrat permanent",
      "discipline": "Conseiller principal d'éducation F/H",
      "date": "14/04/2026",
      "url": "https://talents.aefe.fr/fr/annonce/4329915-assistant-hf-du-directeur-en-charge-de-la-vie-scolaire-20250-casablanca"
    },
    {
      "id": 4329799,
      "titre": "Professeur(e) PHILOSOPHIE LETTRES (F/H) - KENYA - Nairobi - LFIDD",
      "etab": "",
      "ville": "Nairobi",
      "pays": "Kenya",
      "contrat": "Contrat temporaire",
      "discipline": "Professeur de philosophie F/H",
      "date": "14/04/2026",
      "url": "https://talents.aefe.fr/fr/annonce/4329799-professeure-philosophie-lettres-fh-kenya-nairobi-lfidd-nairobi"
    },
    {
      "id": 4329641,
      "titre": "Professeur(e) TECHNOLOGIE MATHEMATIQUES (F/H) - KENYA - Nairobi - LFIDD",
      "etab": "",
      "ville": "Nairobi",
      "pays": "Kenya",
      "contrat": "Contrat temporaire",
      "discipline": "Professeur de technologie F/H",
      "date": "14/04/2026",
      "url": "https://talents.aefe.fr/fr/annonce/4329641-professeure-technologie-mathematiques-fh-kenya-nairobi-lfidd-nairobi"
    },
    {
      "id": 4329503,
      "titre": "Professeur(e) Physique-Chimie (F/H) - KENYA - Nairobi - LFIDD",
      "etab": "",
      "ville": "Nairobi",
      "pays": "Kenya",
      "contrat": "Contrat temporaire",
      "discipline": "Professeur de physique chimie F/H",
      "date": "14/04/2026",
      "url": "https://talents.aefe.fr/fr/annonce/4329503-professeure-physique-chimie-fh-kenya-nairobi-lfidd-nairobi"
    },
    {
      "id": 4329001,
      "titre": "Psychologue Scolaire en Primaire",
      "etab": "",
      "ville": "Singapore",
      "pays": "",
      "contrat": "Contrat permanent",
      "discipline": "Psychologue scolaire F/H",
      "date": "14/04/2026",
      "url": "https://talents.aefe.fr/fr/annonce/4329001-psychologue-scolaire-en-primaire-singapore"
    },
    {
      "id": 4328995,
      "titre": "Psychologue Scolaire du secondaire",
      "etab": "",
      "ville": "Singapore",
      "pays": "",
      "contrat": "Contrat permanent",
      "discipline": "Psychologue scolaire F/H",
      "date": "14/04/2026",
      "url": "https://talents.aefe.fr/fr/annonce/4328995-psychologue-scolaire-du-secondaire-singapore"
    },
    {
      "id": 4328979,
      "titre": "Head of Department French Bilingual Program - Coordinateur de programme bilingue",
      "etab": "",
      "ville": "Tingalpa",
      "pays": "",
      "contrat": "Contrat temporaire",
      "discipline": "Directeur du primaire F/H",
      "date": "14/04/2026",
      "url": "https://talents.aefe.fr/fr/annonce/4328979-head-of-department-french-bilingual-program-coordinateur-de-programme-bilingue-4173-tingalpa"
    },
    {
      "id": 4328947,
      "titre": "Professeur du Second Degré - Mathématiques F/H - SANTIAGO - CHILI",
      "etab": "",
      "ville": "Santiago",
      "pays": "Chili",
      "contrat": "Contrat permanent",
      "discipline": "Professeur de mathématiques F/H",
      "date": "13/04/2026",
      "url": "https://talents.aefe.fr/fr/annonce/4328947-professeur-du-second-degre-mathematiques-fh-santiago-chili-7630599-santiago"
    },
    {
      "id": 4328665,
      "titre": "Professeur du Second Degré ANGLAIS",
      "etab": "",
      "ville": "Mauritania",
      "pays": "",
      "contrat": "Contrat temporaire",
      "discipline": "Professeur du second degré F/H",
      "date": "13/04/2026",
      "url": "https://talents.aefe.fr/fr/annonce/4328665-professeur-du-second-degre-anglais-mauritania"
    },
    {
      "id": 4328651,
      "titre": "Proviseur H/F",
      "etab": "",
      "ville": "Mauritania",
      "pays": "",
      "contrat": "Contrat temporaire",
      "discipline": "Proviseur F/H",
      "date": "13/04/2026",
      "url": "https://talents.aefe.fr/fr/annonce/4328651-proviseur-hf-mauritania"
    },
    {
      "id": 4328637,
      "titre": "Professeur du Second Degré - Physique Chimie F/H - SANTIAGO - CHILI",
      "etab": "",
      "ville": "Santiago",
      "pays": "Chili",
      "contrat": "",
      "discipline": "",
      "date": "13/04/2026",
      "url": "https://talents.aefe.fr/fr/annonce/4328637-professeur-du-second-degre-physique-chimie-fh-santiago-chili-7630599-santiago"
    },
    {
      "id": 4328479,
      "titre": "Chauffeur coursier",
      "etab": "",
      "ville": "Douala",
      "pays": "",
      "contrat": "Contrat permanent",
      "discipline": "Chargé de maintenance et d’entretien F/H",
      "date": "13/04/2026",
      "url": "https://talents.aefe.fr/fr/annonce/4328479-chauffeur-coursier-douala"
    },
    {
      "id": 4328349,
      "titre": "Professeur du Second Degré - Allemand F/H",
      "etab": "",
      "ville": "Douala",
      "pays": "",
      "contrat": "Contrat permanent",
      "discipline": "Professeur du second degré F/H",
      "date": "13/04/2026",
      "url": "https://talents.aefe.fr/fr/annonce/4328349-professeur-du-second-degre-allemand-fh-douala"
    },
    {
      "id": 4328263,
      "titre": "Professeur du Second Degré - Anglais F/H",
      "etab": "",
      "ville": "Douala",
      "pays": "",
      "contrat": "Contrat permanent",
      "discipline": "Professeur du second degré F/H",
      "date": "13/04/2026",
      "url": "https://talents.aefe.fr/fr/annonce/4328263-professeur-du-second-degre-anglais-fh-douala"
    },
    {
      "id": 4328159,
      "titre": "Professeur du Second Degré - Education Physique et Sportive F/H",
      "etab": "",
      "ville": "Douala",
      "pays": "",
      "contrat": "",
      "discipline": "",
      "date": "13/04/2026",
      "url": "https://talents.aefe.fr/fr/annonce/4328159-professeur-du-second-degre-education-physique-et-sportive-fh-douala"
    },
    {
      "id": 4327977,
      "titre": "Professeur du Second Degré - Philosophie F/H",
      "etab": "",
      "ville": "Douala",
      "pays": "",
      "contrat": "Contrat permanent",
      "discipline": "Professeur de philosophie F/H",
      "date": "13/04/2026",
      "url": "https://talents.aefe.fr/fr/annonce/4327977-professeur-du-second-degre-philosophie-fh-douala"
    },
    {
      "id": 4327919,
      "titre": "Professeur du Second Degré - Mathématiques F/H",
      "etab": "",
      "ville": "Douala",
      "pays": "",
      "contrat": "Contrat permanent",
      "discipline": "Professeur de mathématiques F/H",
      "date": "13/04/2026",
      "url": "https://talents.aefe.fr/fr/annonce/4327919-professeur-du-second-degre-mathematiques-fh-douala"
    },
    {
      "id": 4327909,
      "titre": "Professeur de mathématiques- pour le lycée Léon l'Africain de Casablanca",
      "etab": "",
      "ville": "Casablanca",
      "pays": "",
      "contrat": "Contrat permanent",
      "discipline": "Professeur de mathématiques F/H",
      "date": "13/04/2026",
      "url": "https://talents.aefe.fr/fr/annonce/4327909-professeur-de-mathematiques-pour-le-lycee-leon-lafricain-de-casablanca-casablanca"
    },
    {
      "id": 4327707,
      "titre": "Éducateur au Primaire (F/H)",
      "etab": "",
      "ville": "Toronto",
      "pays": "",
      "contrat": "Contrat permanent",
      "discipline": "Aide maternelle F/H",
      "date": "13/04/2026",
      "url": "https://talents.aefe.fr/fr/annonce/4327707-educateur-au-primaire-fh-m6e-3s5-toronto"
    },
    {
      "id": 4327689,
      "titre": "Professeur d'anglais en Primaire (F/H)",
      "etab": "",
      "ville": "Toronto",
      "pays": "",
      "contrat": "Contrat temporaire",
      "discipline": "Professeur d’anglais américain F/H",
      "date": "13/04/2026",
      "url": "https://talents.aefe.fr/fr/annonce/4327689-professeur-danglais-en-primaire-fh-m6e-3s5-toronto"
    },
    {
      "id": 4327645,
      "titre": "Agent d'entretien principal (F/H)",
      "etab": "",
      "ville": "Toronto",
      "pays": "",
      "contrat": "Contrat permanent",
      "discipline": "Chargé de maintenance et d’entretien F/H",
      "date": "13/04/2026",
      "url": "https://talents.aefe.fr/fr/annonce/4327645-agent-dentretien-principal-fh-m6e-3s5-toronto"
    },
    {
      "id": 4327477,
      "titre": "Professeur des écoles",
      "etab": "",
      "ville": "Santo Domingo",
      "pays": "",
      "contrat": "Contrat permanent",
      "discipline": "Professeur des écoles F/H",
      "date": "13/04/2026",
      "url": "https://talents.aefe.fr/fr/annonce/4327477-professeur-des-ecoles-santo-domingo"
    },
    {
      "id": 4327383,
      "titre": "Secrétaire F/H",
      "etab": "",
      "ville": "Santo Domingo",
      "pays": "",
      "contrat": "Contrat permanent",
      "discipline": "Sécrétaire / assistant F/H",
      "date": "13/04/2026",
      "url": "https://talents.aefe.fr/fr/annonce/4327383-secretaire-fh-santo-domingo"
    },
    {
      "id": 4327269,
      "titre": "Professeur en lettres modernes-F/H- Lycée Descartes -Rabat-Maroc 2026/2027",
      "etab": "",
      "ville": "Rabat",
      "pays": "Maroc",
      "contrat": "Contrat temporaire",
      "discipline": "professeur de lettres modernes F/H",
      "date": "13/04/2026",
      "url": "https://talents.aefe.fr/fr/annonce/4327269-professeur-en-lettres-modernes-fh-lycee-descartes-rabat-maroc-20262027-rabat"
    },
    {
      "id": 4327175,
      "titre": "Professeur des écoles - F/H - Lycée de Lusaka - LUSAKA - ZAMBIE SUSCEPTIBLE",
      "etab": "",
      "ville": "Lusaka",
      "pays": "Zambie",
      "contrat": "Contrat temporaire",
      "discipline": "Professeur des écoles F/H",
      "date": "13/04/2026",
      "url": "https://talents.aefe.fr/fr/annonce/4327175-professeur-des-ecoles-fh-lycee-de-lusaka-lusaka-zambie-susceptible-lusaka"
    },
    {
      "id": 4326601,
      "titre": "OUVRIER POLYVALENT - F/H - EGD - ECOLE GEORGES SAND - NABEUL - TUNISIE",
      "etab": "",
      "ville": "Nabeul",
      "pays": "Tunisie",
      "contrat": "Contrat permanent",
      "discipline": "Agent du périscolaire F/H",
      "date": "13/04/2026",
      "url": "https://talents.aefe.fr/fr/annonce/4326601-ouvrier-polyvalent-fh-egd-ecole-georges-sand-nabeul-tunisie-nabeul-"
    },
    {
      "id": 4326291,
      "titre": "Assistant d’Education - F/H - Lycée des Mascareignes - MOKA - ILE MAURICE",
      "etab": "",
      "ville": "Moka",
      "pays": "Île Maurice",
      "contrat": "Contrat temporaire",
      "discipline": "Assistant d'éducation F/H",
      "date": "13/04/2026",
      "url": "https://talents.aefe.fr/fr/annonce/4326291-assistant-d-education-fh-lycee-des-mascareignes-moka-ile-maurice-moka"
    },
    {
      "id": 4326235,
      "titre": "Chargé de communication - F/H - DUBAI - EMIRATS ARABES UNIS",
      "etab": "",
      "ville": "Dubai",
      "pays": "Émirats Arabes Unis",
      "contrat": "Contrat permanent",
      "discipline": "Chargé de communication F/H",
      "date": "13/04/2026",
      "url": "https://talents.aefe.fr/fr/annonce/4326235-charge-de-communication-fh-dubai-emirats-arabes-unis-dubai"
    },
    {
      "id": 4326171,
      "titre": "Professeur des écoles - F/H - ROME -ITALIE",
      "etab": "",
      "ville": "Roma",
      "pays": "Italie",
      "contrat": "Contrat temporaire",
      "discipline": "Professeur des écoles F/H",
      "date": "12/04/2026",
      "url": "https://talents.aefe.fr/fr/annonce/4326171-professeur-des-ecoles-fh-rome-italie-00187-roma"
    },
    {
      "id": 4326167,
      "titre": "Professeur des écoles - primaire (CP) titulaire - F/H - MEDELLIN - COLOMBIE",
      "etab": "",
      "ville": "Envigado",
      "pays": "Colombie",
      "contrat": "Contrat permanent",
      "discipline": "Professeur des écoles F/H",
      "date": "12/04/2026",
      "url": "https://talents.aefe.fr/fr/annonce/4326167-professeur-des-ecoles-primaire-cp-titulaire-fh-medellin-colombie-055427-envigado"
    },
    {
      "id": 4326113,
      "titre": "Professeur d’Anglais - F/H - Native speaker or native alike - CASABLANCA - MAROC",
      "etab": "",
      "ville": "Casablanca",
      "pays": "Maroc",
      "contrat": "Contrat permanent",
      "discipline": "Professeur d’anglais F/H",
      "date": "12/04/2026",
      "url": "https://talents.aefe.fr/fr/annonce/4326113-professeur-d-anglais-fh-native-speaker-or-native-alike-casablanca-maroc-casablanca"
    },
    {
      "id": 4326109,
      "titre": "Professeur de SVT - F/H - CASABLANCA - MAROC",
      "etab": "",
      "ville": "Casablanca",
      "pays": "Maroc",
      "contrat": "Contrat permanent",
      "discipline": "Professeur de sciences de la vie et de la terre F/H",
      "date": "12/04/2026",
      "url": "https://talents.aefe.fr/fr/annonce/4326109-professeur-de-svt-fh-casablanca-maroc-casablanca"
    },
    {
      "id": 4326107,
      "titre": "Professeur de mathématiques - F/H - CASASBLANCA - MAROC",
      "etab": "",
      "ville": "Casablanca",
      "pays": "Maroc",
      "contrat": "Contrat permanent",
      "discipline": "Professeur de mathématiques F/H",
      "date": "12/04/2026",
      "url": "https://talents.aefe.fr/fr/annonce/4326107-professeur-de-mathematiques-fh-casasblanca-maroc-casablanca"
    },
    {
      "id": 4326105,
      "titre": "Professeur de Lettres Modernes - F/H - CASABLANCA - MAROC",
      "etab": "",
      "ville": "Casablanca",
      "pays": "Maroc",
      "contrat": "Contrat permanent",
      "discipline": "professeur de lettres modernes F/H",
      "date": "12/04/2026",
      "url": "https://talents.aefe.fr/fr/annonce/4326105-professeur-de-lettres-modernes-fh-casablanca-maroc-casablanca"
    },
    {
      "id": 4326103,
      "titre": "Professeur de Physique Chimie - F/H - Ecole Al Jabr - CASABLANCA - MAROC",
      "etab": "",
      "ville": "Casablanca",
      "pays": "Maroc",
      "contrat": "Contrat permanent",
      "discipline": "Professeur de physique chimie F/H",
      "date": "12/04/2026",
      "url": "https://talents.aefe.fr/fr/annonce/4326103-professeur-de-physique-chimie-fh-ecole-al-jabr-casablanca-maroc-casablanca"
    },
    {
      "id": 4326101,
      "titre": "Professeur Second Degré d'histoire géographie - F/H - CASABLANCA - MAROC",
      "etab": "",
      "ville": "Casablanca",
      "pays": "Maroc",
      "contrat": "Contrat permanent",
      "discipline": "Professeur d'histoire géographie F/H",
      "date": "12/04/2026",
      "url": "https://talents.aefe.fr/fr/annonce/4326101-professeur-second-degre-dhistoire-geographie-fh-casablanca-maroc-casablanca"
    },
    {
      "id": 4326097,
      "titre": "Professeur du Second Degré - EPS - F/H - Ecole Al Jabr - CASABLANCA - MAROC",
      "etab": "",
      "ville": "Casablanca",
      "pays": "Maroc",
      "contrat": "Contrat permanent",
      "discipline": "Professeur d'éducation physique et sportive F/H",
      "date": "12/04/2026",
      "url": "https://talents.aefe.fr/fr/annonce/4326097-professeur-du-second-degre-eps-fh-ecole-al-jabr-casablanca-maroc-casablanca"
    },
    {
      "id": 4325709,
      "titre": "Professeur du Second Degré - Philosophie - F/H - MANAGUA - NICARAGUA",
      "etab": "",
      "ville": "Managua",
      "pays": "Nicaragua",
      "contrat": "Contrat temporaire",
      "discipline": "Professeur de philosophie F/H",
      "date": "10/04/2026",
      "url": "https://talents.aefe.fr/fr/annonce/4325709-professeur-du-second-degre-philosophie-fh-managua-nicaragua-managua"
    },
    {
      "id": 4325693,
      "titre": "Professeur du Second Degré - Arts Plastiques - F/H - MANAGUA - NICARAGUA",
      "etab": "",
      "ville": "Managua",
      "pays": "Nicaragua",
      "contrat": "Contrat temporaire",
      "discipline": "Professeur d’arts plastiques F/H",
      "date": "10/04/2026",
      "url": "https://talents.aefe.fr/fr/annonce/4325693-professeur-du-second-degre-arts-plastiques-fh-managua-nicaragua-managua"
    },
    {
      "id": 4325563,
      "titre": "Proviseur adjoint - F/H - CASABLANCA - MAROC",
      "etab": "",
      "ville": "Casablanca",
      "pays": "Maroc",
      "contrat": "Contrat permanent",
      "discipline": "Proviseur adjoint F/H",
      "date": "10/04/2026",
      "url": "https://talents.aefe.fr/fr/annonce/4325563-proviseur-adjoint-fh-casablanca-maroc-casablanca"
    },
    {
      "id": 4325559,
      "titre": "Professeur des écoles - MATERNELLE - PS/MS - F/H - VANCOUVER - CANADA",
      "etab": "",
      "ville": "North Vancouver",
      "pays": "Canada",
      "contrat": "Contrat permanent",
      "discipline": "Professeur des écoles F/H",
      "date": "10/04/2026",
      "url": "https://talents.aefe.fr/fr/annonce/4325559-professeur-des-ecoles-maternelle-psms-fh-vancouver-canada-v7k-2e6-north-vancouver"
    },
    {
      "id": 4325021,
      "titre": "Professeur des écoles remplaçant - F/H - VIÑA DEL MAR - CHILI",
      "etab": "",
      "ville": "Viña del Mar",
      "pays": "Chili",
      "contrat": "Contrat temporaire",
      "discipline": "Professeur des écoles F/H",
      "date": "10/04/2026",
      "url": "https://talents.aefe.fr/fr/annonce/4325021-professeur-des-ecoles-remplacant-fh-vina-del-mar-chili-vina-del-mar"
    },
    {
      "id": 4324651,
      "titre": "Assistant Pédagogique - Lycée des Mascareignes - F/H - MOKA - ILE MAURICE",
      "etab": "",
      "ville": "Moka",
      "pays": "Île Maurice",
      "contrat": "Contrat temporaire",
      "discipline": "Assistant d'éducation F/H",
      "date": "10/04/2026",
      "url": "https://talents.aefe.fr/fr/annonce/4324651-assistant-pedagogique-lycee-des-mascareignes-fh-moka-ile-maurice-moka"
    },
    {
      "id": 4324137,
      "titre": "Professeur des écoles– intervention en 6ème (sciences) - F/H - PRISTINA - KOSOVO",
      "etab": "",
      "ville": "Pristina",
      "pays": "Kosovo",
      "contrat": "Contrat temporaire",
      "discipline": "Professeur des écoles F/H",
      "date": "10/04/2026",
      "url": "https://talents.aefe.fr/fr/annonce/4324137-professeur-des-ecoles-intervention-en-6eme-sciences-fh-pristina-kosovo-pristina"
    },
    {
      "id": 4323971,
      "titre": "Intervenant Section Sportive Scolaire Basket Ball - F/H - SALY - SENEGAL",
      "etab": "",
      "ville": "Saly",
      "pays": "Sénégal",
      "contrat": "Contrat temporaire",
      "discipline": "Professeur d'éducation physique et sportive F/H",
      "date": "10/04/2026",
      "url": "https://talents.aefe.fr/fr/annonce/4323971-intervenant-section-sportive-scolaire-basket-ball-fh-saly-senegal-saly"
    },
    {
      "id": 4322967,
      "titre": "Professeur de français - F/H - BCIS - PHUKET - THAILANDE",
      "etab": "",
      "ville": "Chalong",
      "pays": "Thaïlande",
      "contrat": "Contrat temporaire",
      "discipline": "professeur de lettres modernes F/H",
      "date": "10/04/2026",
      "url": "https://talents.aefe.fr/fr/annonce/4322967-professeur-de-francais-fh-bcis-phuket-thailande-83130-chalong"
    },
    {
      "id": 4322645,
      "titre": "PROFESSEUR D'EDUCATION MUSICALE - F/H - BAMAKO - MALI",
      "etab": "",
      "ville": "Bamako",
      "pays": "Mali",
      "contrat": "Contrat temporaire",
      "discipline": "Professeur d'éducation musicale F/H",
      "date": "09/04/2026",
      "url": "https://talents.aefe.fr/fr/annonce/4322645-professeur-deducation-musicale-fh-bamako-mali-bamako"
    },
    {
      "id": 4322609,
      "titre": "Agent spécialisé dans les écoles maternelles (ASEM) - F/H - BAMAKO - MALI",
      "etab": "",
      "ville": "Bamako",
      "pays": "Mali",
      "contrat": "Contrat temporaire",
      "discipline": "Aide maternelle F/H",
      "date": "09/04/2026",
      "url": "https://talents.aefe.fr/fr/annonce/4322609-agent-specialise-dans-les-ecoles-maternelles-asem-fh-bamako-mali-bamako"
    },
    {
      "id": 4322545,
      "titre": "PROFESSEURS DES ECOLES - ETABLISSEMENT LIBERTE - F/H - BAMAKO - MALI",
      "etab": "",
      "ville": "Bamako",
      "pays": "Mali",
      "contrat": "Contrat temporaire",
      "discipline": "Professeur des écoles F/H",
      "date": "09/04/2026",
      "url": "https://talents.aefe.fr/fr/annonce/4322545-professeurs-des-ecoles-etablissement-liberte-fh-bamako-mali-bamako"
    },
    {
      "id": 4322371,
      "titre": "Professeur d’EPS – Collège/Lycée - F/H – BUCAREST - ROUMANIE",
      "etab": "",
      "ville": "București",
      "pays": "Roumanie",
      "contrat": "Contrat permanent",
      "discipline": "Professeur d'éducation physique et sportive F/H",
      "date": "09/04/2026",
      "url": "https://talents.aefe.fr/fr/annonce/4322371-professeur-d-eps-collegelycee-fh-bucarest-roumanie-015016-bucuresti"
    },
    {
      "id": 4321777,
      "titre": "Professeur d'Histoire-Géographie SI américaine - F/H - MANILLE - PHILIPPINES",
      "etab": "",
      "ville": "Parañaque",
      "pays": "Philippines",
      "contrat": "Contrat temporaire",
      "discipline": "Professeur d'histoire géographie F/H",
      "date": "09/04/2026",
      "url": "https://talents.aefe.fr/fr/annonce/4321777-professeur-dhistoire-geographie-si-americaine-fh-manille-philippines-paranaque"
    },
    {
      "id": 4321699,
      "titre": "Enseignant d'anglais non titulaire - F/H - DAKAR - SENEGAL",
      "etab": "",
      "ville": "Dakar",
      "pays": "Sénégal",
      "contrat": "Contrat permanent",
      "discipline": "Professeur des écoles F/H",
      "date": "09/04/2026",
      "url": "https://talents.aefe.fr/fr/annonce/4321699-enseignant-danglais-non-titulaire-fh-dakar-senegal-dakar"
    },
    {
      "id": 4321689,
      "titre": "Professeur des écoles origramme français (non titulaire) - F/H - DAKAR - SENEGAL",
      "etab": "",
      "ville": "Dakar",
      "pays": "Sénégal",
      "contrat": "Contrat permanent",
      "discipline": "Professeur des écoles F/H",
      "date": "09/04/2026",
      "url": "https://talents.aefe.fr/fr/annonce/4321689-professeur-des-ecoles-origramme-francais-non-titulaire-fh-dakar-senegal-dakar"
    },
    {
      "id": 4321525,
      "titre": "Professeur 2nd degré - Physique-Chimie/Technologie - F/H - MANILLE - PHILIPPINES",
      "etab": "",
      "ville": "Parañaque",
      "pays": "Philippines",
      "contrat": "Contrat temporaire",
      "discipline": "Professeur de physique chimie F/H",
      "date": "09/04/2026",
      "url": "https://talents.aefe.fr/fr/annonce/4321525-professeur-2nd-degre-physique-chimietechnologie-fh-manille-philippines-paranaque"
    },
    {
      "id": 4320497,
      "titre": "Professeur du Second Degré - Physique Chimie - F/H - MANAGUA - NICARAGUA",
      "etab": "",
      "ville": "Managua",
      "pays": "Nicaragua",
      "contrat": "Contrat temporaire",
      "discipline": "Professeur de physique chimie F/H",
      "date": "09/04/2026",
      "url": "https://talents.aefe.fr/fr/annonce/4320497-professeur-du-second-degre-physique-chimie-fh-managua-nicaragua-managua"
    },
    {
      "id": 4320489,
      "titre": "Professeur du Second Degré- EPS - F/H - SAN FRANCISCO - CALIFORNIE - ETATS UNIS",
      "etab": "",
      "ville": "San Francisco",
      "pays": "États-Unis",
      "contrat": "Contrat permanent",
      "discipline": "Professeur d'éducation physique et sportive F/H",
      "date": "08/04/2026",
      "url": "https://talents.aefe.fr/fr/annonce/4320489-professeur-du-second-degre-eps-fh-san-francisco-californie-etats-unis-94122-san-francisco"
    },
    {
      "id": 4320243,
      "titre": "Professeur du Second Degré - Lettres Classiques - F/H - BRUXELLES - BELGIQUE",
      "etab": "",
      "ville": "Uccle",
      "pays": "Belgique",
      "contrat": "Contrat temporaire",
      "discipline": "Professeur de lettres classiques F/H",
      "date": "08/04/2026",
      "url": "https://talents.aefe.fr/fr/annonce/4320243-professeur-du-second-degre-lettres-classiques-fh-bruxelles-belgique-1180-uccle"
    },
    {
      "id": 4319995,
      "titre": "Professeur du Second Degré - SVT - F/H - MOSCOU - RUSSIE",
      "etab": "",
      "ville": "Moscow",
      "pays": "Russie",
      "contrat": "Contrat temporaire",
      "discipline": "Professeur de sciences de la vie et de la terre F/H",
      "date": "08/04/2026",
      "url": "https://talents.aefe.fr/fr/annonce/4319995-professeur-du-second-degre-svt-fh-moscou-russie-moscow"
    },
    {
      "id": 4319117,
      "titre": "Conseiller Principal d'Éducation - F/H - CONAKRY - GUINEE",
      "etab": "",
      "ville": "Conakry",
      "pays": "Guinée",
      "contrat": "Contrat temporaire",
      "discipline": "Conseiller principal d'éducation F/H",
      "date": "08/04/2026",
      "url": "https://talents.aefe.fr/fr/annonce/4319117-conseiller-principal-deducation-fh-conakry-guinee-conakry"
    },
    {
      "id": 4318975,
      "titre": "Conseiller Principal d'Éducation - F/H - Lycée Lyautey - CASABLANCA - MAROC",
      "etab": "",
      "ville": "Casablanca",
      "pays": "Maroc",
      "contrat": "Contrat permanent",
      "discipline": "Conseiller principal d'éducation F/H",
      "date": "08/04/2026",
      "url": "https://talents.aefe.fr/fr/annonce/4318975-conseiller-principal-deducation-fh-lycee-lyautey-casablanca-maroc-casablanca"
    },
    {
      "id": 4318913,
      "titre": "Professeur du Second Degré - Lettres - F/H - MANILLE - PHILIPPINES",
      "etab": "",
      "ville": "Parañaque",
      "pays": "Philippines",
      "contrat": "Contrat temporaire",
      "discipline": "professeur de lettres modernes F/H",
      "date": "08/04/2026",
      "url": "https://talents.aefe.fr/fr/annonce/4318913-professeur-du-second-degre-lettres-fh-manille-philippines-paranaque"
    },
    {
      "id": 4318897,
      "titre": "PROFESSEUR D'EPS - F/H - ORAN - ALGERIE",
      "etab": "",
      "ville": "Ben Aknoun",
      "pays": "Algérie",
      "contrat": "Contrat permanent",
      "discipline": "Professeur d'éducation physique et sportive F/H",
      "date": "08/04/2026",
      "url": "https://talents.aefe.fr/fr/annonce/4318897-professeur-deps-fh-oran-algerie-ben-aknoun"
    },
    {
      "id": 4318837,
      "titre": "Professeur de Lettres - F/H - Lycée Louis Massignon - ABU DHABI - EAU",
      "etab": "",
      "ville": "Abu Dhabi",
      "pays": "Émirats Arabes Unis",
      "contrat": "Contrat temporaire",
      "discipline": "professeur de lettres modernes F/H",
      "date": "08/04/2026",
      "url": "https://talents.aefe.fr/fr/annonce/4318837-professeur-de-lettres-fh-lycee-louis-massignon-abu-dhabi-eau-abu-dhabi"
    },
    {
      "id": 4318807,
      "titre": "Professeur de SVT - F/H - ORAN - ALGERIE",
      "etab": "",
      "ville": "Ben Aknoun",
      "pays": "Algérie",
      "contrat": "Contrat permanent",
      "discipline": "Professeur de sciences de la vie et de la terre F/H",
      "date": "08/04/2026",
      "url": "https://talents.aefe.fr/fr/annonce/4318807-professeur-de-svt-fh-oran-algerie-ben-aknoun"
    },
    {
      "id": 4318729,
      "titre": "Professeur Sciences physiques et chimie - F/H - ORAN - ALGERIE",
      "etab": "",
      "ville": "Ben Aknoun",
      "pays": "Algérie",
      "contrat": "Contrat permanent",
      "discipline": "Professeur de physique chimie F/H",
      "date": "08/04/2026",
      "url": "https://talents.aefe.fr/fr/annonce/4318729-professeur-sciences-physiques-et-chimie-fh-oran-algerie-ben-aknoun"
    },
    {
      "id": 4318697,
      "titre": "Conseiller Principal d'Éducation - F/H - ABIDJAN - CÔTE D'IVOIRE",
      "etab": "",
      "ville": "Abidjan",
      "pays": "Côte d'Ivoire",
      "contrat": "Contrat temporaire",
      "discipline": "Conseiller principal d'éducation F/H",
      "date": "08/04/2026",
      "url": "https://talents.aefe.fr/fr/annonce/4318697-conseiller-principal-deducation-fh-abidjan-cote-divoire-bp-157-abidjan"
    },
    {
      "id": 4318235,
      "titre": "Poste de professeur des écoles - F/H - NEW DELHI - INDE",
      "etab": "",
      "ville": "New Delhi",
      "pays": "Inde",
      "contrat": "Contrat temporaire",
      "discipline": "Professeur des écoles F/H",
      "date": "08/04/2026",
      "url": "https://talents.aefe.fr/fr/annonce/4318235-poste-de-professeur-des-ecoles-fh-new-delhi-inde-110011-new-delhi"
    },
    {
      "id": 4317967,
      "titre": "Directeur Administratif et Financier - F/H - BAMAKO - MALI",
      "etab": "",
      "ville": "Bamako",
      "pays": "Mali",
      "contrat": "Contrat temporaire",
      "discipline": "Directeur Administratif et Financier F/H",
      "date": "07/04/2026",
      "url": "https://talents.aefe.fr/fr/annonce/4317967-directeur-administratif-et-financier-fh-bamako-mali-bamako"
    },
    {
      "id": 4317961,
      "titre": "Professeur de Physique Chimie - F/H - VILLANUEVA DE LA CAÑADA - ESPAGNE",
      "etab": "",
      "ville": "Villanueva de la Cañada",
      "pays": "Espagne",
      "contrat": "Contrat temporaire",
      "discipline": "Professeur de physique chimie F/H",
      "date": "07/04/2026",
      "url": "https://talents.aefe.fr/fr/annonce/4317961-professeur-de-physique-chimie-fh-villanueva-de-la-canada-espagne-28691-villanueva-de-la-canada"
    },
    {
      "id": 4317759,
      "titre": "Professeur de mathématiques - F/H - ORAN - ALGERIE",
      "etab": "",
      "ville": "Ben Aknoun",
      "pays": "Algérie",
      "contrat": "Contrat permanent",
      "discipline": "Professeur du second degré F/H",
      "date": "07/04/2026",
      "url": "https://talents.aefe.fr/fr/annonce/4317759-professeur-de-mathematiques-fh-oran-algerie-ben-aknoun"
    },
    {
      "id": 4317681,
      "titre": "PROFESSEUR DE SES -F/H - ALGER - ALGERIE",
      "etab": "",
      "ville": "Ben Aknoun",
      "pays": "Algérie",
      "contrat": "Contrat permanent",
      "discipline": "Professeur Sciences économiques et sociales F/H",
      "date": "07/04/2026",
      "url": "https://talents.aefe.fr/fr/annonce/4317681-professeur-de-ses-fh-alger-algerie-ben-aknoun"
    },
    {
      "id": 4317433,
      "titre": "Professeur d'arabe - F/H - ALGER - ALGERIE",
      "etab": "",
      "ville": "Ben Aknoun",
      "pays": "Algérie",
      "contrat": "Contrat permanent",
      "discipline": "Professeur d’arabe F/H",
      "date": "07/04/2026",
      "url": "https://talents.aefe.fr/fr/annonce/4317433-professeur-darabe-fh-alger-algerie-ben-aknoun"
    },
    {
      "id": 4317405,
      "titre": "Professeur d'histoire géographie - F/H - ALGER - ALGERIE",
      "etab": "",
      "ville": "Ben Aknoun",
      "pays": "Algérie",
      "contrat": "Contrat permanent",
      "discipline": "Professeur d'histoire géographie F/H",
      "date": "07/04/2026",
      "url": "https://talents.aefe.fr/fr/annonce/4317405-professeur-dhistoire-geographie-fh-alger-algerie-ben-aknoun"
    },
    {
      "id": 4317343,
      "titre": "Professeur d'anglais - F/H - ALGER - ALGERIE",
      "etab": "",
      "ville": "Ben Aknoun",
      "pays": "Algérie",
      "contrat": "Contrat permanent",
      "discipline": "Professeur d’anglais F/H",
      "date": "07/04/2026",
      "url": "https://talents.aefe.fr/fr/annonce/4317343-professeur-danglais-fh-alger-algerie-ben-aknoun"
    },
    {
      "id": 4316973,
      "titre": "Professeur du Second Degré - Mathématiques - F/H - TIRANA - ALBANIE",
      "etab": "",
      "ville": "Lundër 1",
      "pays": "Albanie",
      "contrat": "Contrat permanent",
      "discipline": "Professeur de mathématiques F/H",
      "date": "07/04/2026",
      "url": "https://talents.aefe.fr/fr/annonce/4316973-professeur-du-second-degre-mathematiques-fh-tirana-albanie-lunder-1"
    },
    {
      "id": 4316851,
      "titre": "Professeur des écoles-F/H - Lycée Français International d'Accra - ACCRA - GHANA",
      "etab": "",
      "ville": "Accra",
      "pays": "Ghana",
      "contrat": "Contrat permanent",
      "discipline": "Professeur des écoles F/H",
      "date": "07/04/2026",
      "url": "https://talents.aefe.fr/fr/annonce/4316851-professeur-des-ecoles-fh-lycee-francais-international-daccra-accra-ghana-accra"
    },
    {
      "id": 4316747,
      "titre": "Professeurs du second degré de Lettres - F/H - SOUSSE - TUNISIE",
      "etab": "",
      "ville": "Sousse",
      "pays": "Tunisie",
      "contrat": "Contrat permanent",
      "discipline": "Professeur du second degré F/H",
      "date": "07/04/2026",
      "url": "https://talents.aefe.fr/fr/annonce/4316747-professeurs-du-second-degre-de-lettres-fh-sousse-tunisie-4023-sousse"
    },
    {
      "id": 4316557,
      "titre": "Professeur de SES - Lycée Voltaire - F/H - LE CAIRE - EGYPTE",
      "etab": "",
      "ville": "Cairo",
      "pays": "Égypte",
      "contrat": "Contrat temporaire",
      "discipline": "Professeur Sciences économiques et sociales F/H",
      "date": "07/04/2026",
      "url": "https://talents.aefe.fr/fr/annonce/4316557-professeur-de-ses-lycee-voltaire-fh-le-caire-egypte-cairo"
    },
    {
      "id": 4316101,
      "titre": "Professeur du Second Degré - SVT - F/H - DJERBA - TUNISIE",
      "etab": "",
      "ville": "Houmt Souk",
      "pays": "Tunisie",
      "contrat": "Contrat permanent",
      "discipline": "Professeur de sciences de la vie et de la terre F/H",
      "date": "07/04/2026",
      "url": "https://talents.aefe.fr/fr/annonce/4316101-professeur-du-second-degre-svt-fh-djerba-tunisie-4180-houmt-souk"
    },
    {
      "id": 4315877,
      "titre": "Professeur du Second Degré d'H-G - F/H - NOUAKCHOTT - MAURITANIE",
      "etab": "",
      "ville": "Mauritania",
      "pays": "Mauritanie",
      "contrat": "Contrat permanent",
      "discipline": "Professeur d'histoire géographie F/H",
      "date": "07/04/2026",
      "url": "https://talents.aefe.fr/fr/annonce/4315877-professeur-du-second-degre-dh-g-fh-nouakchott-mauritanie-mauritania"
    },
    {
      "id": 4315509,
      "titre": "CPE - F/H - KUALA LUMPUR - MALAISIE",
      "etab": "",
      "ville": "Kuala Lumpur",
      "pays": "Malaisie",
      "contrat": "Contrat temporaire",
      "discipline": "Conseiller principal d'éducation F/H",
      "date": "07/04/2026",
      "url": "https://talents.aefe.fr/fr/annonce/4315509-cpe-fh-kuala-lumpur-malaisie-kuala-lumpur"
    },
    {
      "id": 4315507,
      "titre": "Professeur des écoles - Maternelle - F/H - RANGOUN (YANGON) - BIRMANIE (MYANMAR)",
      "etab": "",
      "ville": "Yangon",
      "pays": "Myanmar",
      "contrat": "Contrat permanent",
      "discipline": "Professeur des écoles F/H",
      "date": "07/04/2026",
      "url": "https://talents.aefe.fr/fr/annonce/4315507-professeur-des-ecoles-maternelle-fh-rangoun-yangon-birmanie-myanmar-yangon"
    },
    {
      "id": 4315407,
      "titre": "Directeur du Primaire: TPS-CM2-26-27 - F/H - BOSTON - MASSACHUSETTS - ETATS-UNIS",
      "etab": "",
      "ville": "Cambridge",
      "pays": "États-Unis",
      "contrat": "Contrat permanent",
      "discipline": "Directeur du primaire F/H",
      "date": "06/04/2026",
      "url": "https://talents.aefe.fr/fr/annonce/4315407-directeur-du-primaire-tps-cm2-26-27-fh-boston-massachusetts-etats-unis-02140-cambridge"
    },
    {
      "id": 4284955,
      "titre": "Professeur des écoles - F/H - PRAIA - CAP-VERT",
      "etab": "",
      "ville": "Praia",
      "pays": "",
      "contrat": "Contrat temporaire",
      "discipline": "Professeur des écoles F/H",
      "date": "07/04/2026",
      "url": "https://talents.aefe.fr/fr/annonce/4284955-professeur-des-ecoles-fh-praia-cap-vert-praia"
    },
    {
      "id": 4279055,
      "titre": "Professeur du Second Degré - Mathématiques - F/H - TOKYO - JAPON",
      "etab": "",
      "ville": "Kita City",
      "pays": "Japon",
      "contrat": "Contrat temporaire",
      "discipline": "Professeur de mathématiques F/H",
      "date": "10/04/2026",
      "url": "https://talents.aefe.fr/fr/annonce/4279055-professeur-du-second-degre-mathematiques-fh-tokyo-japon-114-0023-kita-city"
    },
    {
      "id": 4272313,
      "titre": "Professeur du Second Degré - Lettres Modernes - F/H - BRUXELLES - BELGIQUE",
      "etab": "",
      "ville": "Uccle",
      "pays": "Belgique",
      "contrat": "Contrat temporaire",
      "discipline": "professeur de lettres modernes F/H",
      "date": "08/04/2026",
      "url": "https://talents.aefe.fr/fr/annonce/4272313-professeur-du-second-degre-lettres-modernes-fh-bruxelles-belgique-1180-uccle"
    },
    {
      "id": 4230967,
      "titre": "Professeur d'ANGLAIS 1er degré - F/H - ABIDJAN - CÔTE D'IVOIRE",
      "etab": "",
      "ville": "Abidjan",
      "pays": "Côte d'Ivoire",
      "contrat": "Contrat temporaire",
      "discipline": "Professeur d’anglais britannique F/H",
      "date": "08/04/2026",
      "url": "https://talents.aefe.fr/fr/annonce/4230967-professeur-danglais-1er-degre-fh-abidjan-cote-divoire-bp-157-abidjan"
    },
    {
      "id": 4218125,
      "titre": "Professeur des écoles F/H - MANILLE - PHILIPPINES",
      "etab": "",
      "ville": "Parañaque",
      "pays": "Philippines",
      "contrat": "Contrat temporaire",
      "discipline": "Professeur des écoles F/H",
      "date": "09/04/2026",
      "url": "https://talents.aefe.fr/fr/annonce/4218125-professeur-des-ecoles-fh-manille-philippines-paranaque"
    },
    {
      "id": 4218063,
      "titre": "Professeur 2nd degré - EPS - F/H - MANILLE - PHILIPPINES",
      "etab": "",
      "ville": "Parañaque",
      "pays": "Philippines",
      "contrat": "Contrat temporaire",
      "discipline": "Professeur d'éducation physique et sportive F/H",
      "date": "09/04/2026",
      "url": "https://talents.aefe.fr/fr/annonce/4218063-professeur-2nd-degre-eps-fh-manille-philippines-paranaque"
    },
    {
      "id": 4216513,
      "titre": "Professeur 2nd degré - Mathématiques/Technologie - F/H - MANILLE - PHILIPPINES",
      "etab": "",
      "ville": "Parañaque",
      "pays": "Philippines",
      "contrat": "Contrat temporaire",
      "discipline": "Professeur de mathématiques F/H",
      "date": "09/04/2026",
      "url": "https://talents.aefe.fr/fr/annonce/4216513-professeur-2nd-degre-mathematiquestechnologie-fh-manille-philippines-paranaque"
    },
    {
      "id": 4216473,
      "titre": "Professeur du 2nd degré - Anglais américain - F/H - MANILLE - PHILIPPINES",
      "etab": "",
      "ville": "Parañaque",
      "pays": "Philippines",
      "contrat": "Contrat temporaire",
      "discipline": "Professeur d’anglais américain F/H",
      "date": "09/04/2026",
      "url": "https://talents.aefe.fr/fr/annonce/4216473-professeur-du-2nd-degre-anglais-americain-fh-manille-philippines-paranaque"
    },
    {
      "id": 4216329,
      "titre": "Professeur du 2nd degré - Histoire-Géographie - F/H - MANILLE - PHILIPPINES",
      "etab": "",
      "ville": "Parañaque",
      "pays": "Philippines",
      "contrat": "Contrat temporaire",
      "discipline": "Professeur d'histoire géographie F/H",
      "date": "09/04/2026",
      "url": "https://talents.aefe.fr/fr/annonce/4216329-professeur-du-2nd-degre-histoire-geographie-fh-manille-philippines-paranaque"
    },
    {
      "id": 4216297,
      "titre": "Professeur du 2nd degré - SES - F/H - MANILLE - PHILIPPINES",
      "etab": "",
      "ville": "Parañaque",
      "pays": "Philippines",
      "contrat": "Contrat temporaire",
      "discipline": "Professeur Sciences économiques et sociales F/H",
      "date": "09/04/2026",
      "url": "https://talents.aefe.fr/fr/annonce/4216297-professeur-du-2nd-degre-ses-fh-manille-philippines-paranaque"
    },
    {
      "id": 4215647,
      "titre": "Professeur du 2nd degré - Mathématiques/NSI - F/H - MANILLE - PHILIPPINES",
      "etab": "",
      "ville": "Parañaque",
      "pays": "Philippines",
      "contrat": "Contrat temporaire",
      "discipline": "Professeur de mathématiques F/H",
      "date": "09/04/2026",
      "url": "https://talents.aefe.fr/fr/annonce/4215647-professeur-du-2nd-degre-mathematiquesnsi-fh-manille-philippines-paranaque"
    },
    {
      "id": 4206229,
      "titre": "Conseiller principal d’éducation - F/H - CASABLANCA - MAROC",
      "etab": "",
      "ville": "Casablanca",
      "pays": "Maroc",
      "contrat": "Contrat permanent",
      "discipline": "Conseiller principal d'éducation F/H",
      "date": "07/04/2026",
      "url": "https://talents.aefe.fr/fr/annonce/4206229-conseiller-principal-d-education-fh-casablanca-maroc-casablanca"
    },
    {
      "id": 4205105,
      "titre": "enseignant en Lettres-Philosophie - F/H - CUENCA - EQUATEUR",
      "etab": "",
      "ville": "Cuenca",
      "pays": "Équateur",
      "contrat": "Contrat permanent",
      "discipline": "Professeur du second degré F/H",
      "date": "10/04/2026",
      "url": "https://talents.aefe.fr/fr/annonce/4205105-enseignant-en-lettres-philosophie-fh-cuenca-equateur-cuenca"
    },
    {
      "id": 4203629,
      "titre": "Professeur de Mathématiques F/H – LONDRES - ROYAUME-UNI",
      "etab": "",
      "ville": "England",
      "pays": "Royaume-Uni",
      "contrat": "Contrat permanent",
      "discipline": "Professeur de mathématiques F/H",
      "date": "14/04/2026",
      "url": "https://talents.aefe.fr/fr/annonce/4203629-professeur-de-mathematiques-fh-londres-royaume-uni-greater-london"
    },
    {
      "id": 4182379,
      "titre": "Professeur du Second Degré d'histoire géographie F/H - CALI (Yumbo) - COLOMBIE",
      "etab": "",
      "ville": "Cali",
      "pays": "Colombie",
      "contrat": "Contrat temporaire",
      "discipline": "Professeur d'histoire géographie F/H",
      "date": "13/04/2026",
      "url": "https://talents.aefe.fr/fr/annonce/4182379-professeur-du-second-degre-dhistoire-geographie-fh-cali-yumbo-colombie-760042-cali"
    },
    {
      "id": 4164859,
      "titre": "Professeur d'histoire géographie - F/H - DUBAI - EMIRATS ARABES UNIS",
      "etab": "",
      "ville": "Dubai",
      "pays": "Émirats Arabes Unis",
      "contrat": "Contrat permanent",
      "discipline": "Professeur d'histoire géographie F/H",
      "date": "13/04/2026",
      "url": "https://talents.aefe.fr/fr/annonce/4164859-professeur-dhistoire-geographie-fh-dubai-emirats-arabes-unis-dubai"
    },
    {
      "id": 4154577,
      "titre": "Directeur adjoint en charge de l'école maternelle - F/H - CASABLANCA - MAROC",
      "etab": "",
      "ville": "Casablanca",
      "pays": "Maroc",
      "contrat": "Contrat permanent",
      "discipline": "Principal adjoint F/H",
      "date": "07/04/2026",
      "url": "https://talents.aefe.fr/fr/annonce/4154577-directeur-adjoint-en-charge-de-lecole-maternelle-fh-casablanca-maroc-casablanca"
    },
    {
      "id": 4154369,
      "titre": "Enseignant en Mathématiques Rentrée 2026/2027 - F/H - KUALA LUMPUR - MALAISIE",
      "etab": "",
      "ville": "Kuala Lumpur",
      "pays": "Malaisie",
      "contrat": "Contrat temporaire",
      "discipline": "Professeur du second degré F/H",
      "date": "13/04/2026",
      "url": "https://talents.aefe.fr/fr/annonce/4154369-enseignant-en-mathematiques-rentree-20262027-fh-kuala-lumpur-malaisie-kuala-lumpur"
    },
    {
      "id": 4151931,
      "titre": "Professeur de SNT - F/H - COTONOU - BENIN",
      "etab": "",
      "ville": "Cotonou",
      "pays": "Bénin",
      "contrat": "Contrat permanent",
      "discipline": "Professeur de Sciences Numériques et Technologie F/H",
      "date": "11/04/2026",
      "url": "https://talents.aefe.fr/fr/annonce/4151931-professeur-de-snt-fh-cotonou-benin-9087-cotonou"
    },
    {
      "id": 4151923,
      "titre": "Professeur d'histoire géographie - F/H - COTONOU - BENIN",
      "etab": "",
      "ville": "Cotonou",
      "pays": "Bénin",
      "contrat": "Contrat permanent",
      "discipline": "Professeur d'histoire géographie F/H",
      "date": "11/04/2026",
      "url": "https://talents.aefe.fr/fr/annonce/4151923-professeur-dhistoire-geographie-fh-cotonou-benin-9087-cotonou"
    },
    {
      "id": 4148919,
      "titre": "ASSISTANT MATERNELLE - F/H - PORTLAND - OREGON - ETATS UNIS",
      "etab": "",
      "ville": "Portland",
      "pays": "États-Unis",
      "contrat": "Contrat temporaire",
      "discipline": "Assistant d'éducation F/H",
      "date": "07/04/2026",
      "url": "https://talents.aefe.fr/fr/annonce/4148919-assistant-maternelle-fh-portland-oregon-etats-unis-97239-portland"
    },
    {
      "id": 4148915,
      "titre": "PROFESSEUR DES ECOLES - F/H - PORTLAND - OREGON - ETATS-UNIS",
      "etab": "",
      "ville": "Portland",
      "pays": "États-Unis",
      "contrat": "Contrat permanent",
      "discipline": "Professeur des écoles F/H",
      "date": "07/04/2026",
      "url": "https://talents.aefe.fr/fr/annonce/4148915-professeur-des-ecoles-fh-portland-oregon-etats-unis-97239-portland"
    },
    {
      "id": 4143823,
      "titre": "Professeur de philosophie - F/H - COTONOU - BENIN",
      "etab": "",
      "ville": "Cotonou",
      "pays": "Bénin",
      "contrat": "Contrat permanent",
      "discipline": "Professeur de philosophie F/H",
      "date": "11/04/2026",
      "url": "https://talents.aefe.fr/fr/annonce/4143823-professeur-de-philosophie-fh-cotonou-benin-9087-cotonou"
    },
    {
      "id": 4142975,
      "titre": "Professeur des écoles - Rentrée 2026/2027 - F/H - COTONOU - BENIN",
      "etab": "",
      "ville": "Cotonou",
      "pays": "Bénin",
      "contrat": "Contrat permanent",
      "discipline": "Professeur des écoles F/H",
      "date": "11/04/2026",
      "url": "https://talents.aefe.fr/fr/annonce/4142975-professeur-des-ecoles-rentree-20262027-fh-cotonou-benin-9087-cotonou"
    },
    {
      "id": 4138141,
      "titre": "Proviseur adjoint - F/H - CASABLANCA - MAROC",
      "etab": "",
      "ville": "Casablanca",
      "pays": "Maroc",
      "contrat": "Contrat permanent",
      "discipline": "Proviseur adjoint F/H",
      "date": "07/04/2026",
      "url": "https://talents.aefe.fr/fr/annonce/4138141-proviseur-adjoint-fh-casablanca-maroc-casablanca"
    },
    {
      "id": 4136475,
      "titre": "Professeur de Mathématiques - F/H - CASABLANCA - MAROC",
      "etab": "",
      "ville": "Casablanca",
      "pays": "Maroc",
      "contrat": "Contrat permanent",
      "discipline": "Professeur de mathématiques F/H",
      "date": "07/04/2026",
      "url": "https://talents.aefe.fr/fr/annonce/4136475-professeur-de-mathematiques-fh-casablanca-maroc-casablanca"
    },
    {
      "id": 4108363,
      "titre": "Professeur de Lettres Modernes- F/H - ABIDJAN - CÔTE D'IVOIRE",
      "etab": "",
      "ville": "Abidjan",
      "pays": "Côte d'Ivoire",
      "contrat": "Contrat temporaire",
      "discipline": "professeur de lettres modernes F/H",
      "date": "07/04/2026",
      "url": "https://talents.aefe.fr/fr/annonce/4108363-professeur-de-lettres-modernes-fh-abidjan-cote-divoire-abidjan"
    },
    {
      "id": 4098191,
      "titre": "Professeur des écoles - F/H - VICTORIA - SEYCHELLES",
      "etab": "",
      "ville": "Seychelles",
      "pays": "Seychelles",
      "contrat": "Contrat temporaire",
      "discipline": "Professeur des écoles F/H",
      "date": "09/04/2026",
      "url": "https://talents.aefe.fr/fr/annonce/4098191-professeur-des-ecoles-fh-victoria-seychelles-seychelles"
    },
    {
      "id": 4093183,
      "titre": "AIDE-LABORATOIRE - F/H - Lycée français Jacques-Prévert - SALY - SENEGAL",
      "etab": "",
      "ville": "Saly",
      "pays": "Sénégal",
      "contrat": "Contrat temporaire",
      "discipline": "Aide de laboratoire F/H",
      "date": "13/04/2026",
      "url": "https://talents.aefe.fr/fr/annonce/4093183-aide-laboratoire-fh-lycee-francais-jacques-prevert-saly-senegal-saly"
    },
    {
      "id": 4068009,
      "titre": "Professeur du Second Degré Mathématiques - F/H - ABIDJAN - CÔTE D'IVOIRE (2 PSV)",
      "etab": "",
      "ville": "Abidjan",
      "pays": "Côte d'Ivoire",
      "contrat": "Contrat temporaire",
      "discipline": "Professeur de mathématiques F/H",
      "date": "07/04/2026",
      "url": "https://talents.aefe.fr/fr/annonce/4068009-professeur-du-second-degre-mathematiques-fh-abidjan-cote-divoire-2-psv-abidjan"
    },
    {
      "id": 4001511,
      "titre": "Professeur des écoles - ICE SCHOOL - F/H - DUBAÏ - EMIRATS ARABES UNIS",
      "etab": "",
      "ville": "Dubai",
      "pays": "Émirats Arabes Unis",
      "contrat": "Contrat permanent",
      "discipline": "Professeur des écoles F/H",
      "date": "13/04/2026",
      "url": "https://talents.aefe.fr/fr/annonce/4001511-professeur-des-ecoles-ice-school-fh-dubai-emirats-arabes-unis-dubai"
    },
    {
      "id": 3725161,
      "titre": "Professeur du 2nd Degré - SES - F/H - SEOUL - COREE DU SUD",
      "etab": "",
      "ville": "Seoul",
      "pays": "Corée du Sud",
      "contrat": "Contrat temporaire",
      "discipline": "Professeur Sciences économiques et sociales F/H",
      "date": "13/04/2026",
      "url": "https://talents.aefe.fr/fr/annonce/3725161-professeur-du-2nd-degre-ses-fh-seoul-coree-du-sud-seoul"
    },
    {
      "id": 3718385,
      "titre": "Professeur d'Arabe F/H - CASABLANCA - MAROC",
      "etab": "",
      "ville": "Casablanca",
      "pays": "Maroc",
      "contrat": "Contrat permanent",
      "discipline": "Professeur d’arabe F/H",
      "date": "13/04/2026",
      "url": "https://talents.aefe.fr/fr/annonce/3718385-professeur-darabe-fh-casablanca-maroc-casablanca"
    },
    {
      "id": 3486827,
      "titre": "Professeur du Second Degré Sciences - F/H - SARAJEVO - BOSNIE-HERZÉGOVINE",
      "etab": "",
      "ville": "Sarajevo",
      "pays": "Bosnie-Herzégovine",
      "contrat": "Contrat temporaire",
      "discipline": "Professeur de Sciences Numériques et Technologie F/H",
      "date": "07/04/2026",
      "url": "https://talents.aefe.fr/fr/annonce/3486827-professeur-du-second-degre-sciences-fh-sarajevo-bosnie-herzegovine-71000-sarajevo"
    },
    {
      "id": 3486789,
      "titre": "Professeur Mathématiques Physique-Chimie - F/H - SARAJEVO - BOSNIE-HERZÉGOVINE",
      "etab": "",
      "ville": "Sarajevo",
      "pays": "Bosnie-Herzégovine",
      "contrat": "Contrat temporaire",
      "discipline": "Professeur de mathématiques F/H",
      "date": "07/04/2026",
      "url": "https://talents.aefe.fr/fr/annonce/3486789-professeur-mathematiques-physique-chimie-fh-sarajevo-bosnie-herzegovine-71000-sarajevo"
    },
    {
      "id": 3486785,
      "titre": "Professeur du Second Degré Physique Chimie -F/H - SARAJEVO - BOSNIE-HERZÉGOVINE",
      "etab": "",
      "ville": "Sarajevo",
      "pays": "Bosnie-Herzégovine",
      "contrat": "Contrat temporaire",
      "discipline": "Professeur de physique chimie F/H",
      "date": "07/04/2026",
      "url": "https://talents.aefe.fr/fr/annonce/3486785-professeur-du-second-degre-physique-chimie-fh-sarajevo-bosnie-herzegovine-71000-sarajevo"
    },
    {
      "id": 3486777,
      "titre": "Professeur 2nd Degré Histoire-Géographie - F/H - SARAJEVO - BOSNIE-HERZÉGOVINE",
      "etab": "",
      "ville": "Sarajevo",
      "pays": "Bosnie-Herzégovine",
      "contrat": "Contrat temporaire",
      "discipline": "Professeur d'histoire géographie F/H",
      "date": "10/04/2026",
      "url": "https://talents.aefe.fr/fr/annonce/3486777-professeur-2nd-degre-histoire-geographie-fh-sarajevo-bosnie-herzegovine-71000-sarajevo"
    }
  ]
}